tester_story_sdk
