Metadata-Version: 2.1
Name: tester-story-sdk
Version: 0.1.6
Summary: A Python SDK for interacting with the Story Protocol.
Home-page: https://github.com/aandrewchung/python-sdk/tree/andrew/pip-install
Author: Andrew Chung
Author-email: andrew@storyprotocol.xyz
License: MIT
Classifier: Programming Language :: Python :: 3
Classifier: License :: OSI Approved :: MIT License
Classifier: Operating System :: OS Independent
Requires-Python: >=3.6
License-File: LICENSE
Requires-Dist: web3>=5.0.0
Requires-Dist: pytest
Requires-Dist: python-dotenv
